ragbits/conversations/__init__.py
ragbits/conversations/py.typed
ragbits/conversations/history/__init__.py
ragbits/conversations/history/compressors/__init__.py
ragbits/conversations/history/compressors/base.py
ragbits/conversations/history/compressors/llm.py
ragbits/conversations/history/stores/__init__.py
ragbits/conversations/history/stores/base.py
ragbits/conversations/history/stores/sql.py
ragbits_conversations-0.13.0.dist-info/METADATA
ragbits_conversations-0.13.0.dist-info/WHEEL
ragbits_conversations-0.13.0.dist-info/RECORD
