Metadata-Version: 2.4
Name: ragbits-conversations
Version: 0.13.0
Summary: Building blocks for rapid development of GenAI applications
Project-URL: Homepage, https://github.com/deepsense-ai/ragbits
Project-URL: Bug Reports, https://github.com/deepsense-ai/ragbits/issues
Project-URL: Documentation, https://ragbits.deepsense.ai/
Project-URL: Source, https://github.com/deepsense-ai/ragbits
Author-email: "deepsense.ai" <ragbits@deepsense.ai>
License-Expression: MIT
Keywords: GenAI,Generative AI,LLMs,Large Language Models,Prompt Management,RAG,Retrieval Augmented Generation
Classifier: Development Status :: 4 - Beta
Classifier: Environment :: Console
Classifier: Intended Audience :: Science/Research
Classifier: License :: OSI Approved :: MIT License
Classifier: Natural Language :: English
Classifier: Operating System :: OS Independent
Classifier: Programming Language :: Python :: 3.10
Classifier: Programming Language :: Python :: 3.11
Classifier: Programming Language :: Python :: 3.12
Classifier: Programming Language :: Python :: 3.13
Classifier: Topic :: Scientific/Engineering :: Artificial Intelligence
Classifier: Topic :: Software Development :: Libraries :: Python Modules
Requires-Python: >=3.10
Requires-Dist: ragbits-core==0.13.0
